awschain/__init__.py
awschain/handlers/__init__.py
awschain/handlers/abstract_handler.py
awschain/handlers/base_handler.py
awschain/handlers/handler_factory.py
awschain/handlers/misc/__init__.py
awschain/handlers/misc/clipboard_writer_handler.py
awschain/handlers/misc/print_context_handler.py
awschain/handlers/misc/remote_file_downloader_handler.py
awschain/handlers/processors/__init__.py
awschain/handlers/processors/amazon_bedrock_chat_handler.py
awschain/handlers/processors/amazon_bedrock_handler.py
awschain/handlers/processors/amazon_comprehend_insights_handler.py
awschain/handlers/processors/amazon_comprehend_pii_classifier_handler.py
awschain/handlers/processors/amazon_comprehend_pii_handler.py
awschain/handlers/processors/amazon_comprehend_pii_tokenize_handler.py
awschain/handlers/processors/amazon_comprehend_pii_untokenize_handler.py
awschain/handlers/processors/amazon_rekognition_handler.py
awschain/handlers/processors/amazon_textract_handler.py
awschain/handlers/processors/amazon_transcribe_handler.py
awschain/handlers/processors/anonymize_handler.py
awschain/handlers/processors/html_cleaner_handler.py
awschain/handlers/processors/prompt_handler.py
awschain/handlers/readers/__init__.py
awschain/handlers/readers/amazon_s3_reader_handler.py
awschain/handlers/readers/aws_secrets_manager_secret_reader.py
awschain/handlers/readers/email_reader_handler.py
awschain/handlers/readers/http_handler.py
awschain/handlers/readers/local_file_reader_handler.py
awschain/handlers/readers/microsoft_excel_reader_handler.py
awschain/handlers/readers/microsoft_power_point_reader_handler.py
awschain/handlers/readers/microsoft_word_handler.py
awschain/handlers/readers/pdf_reader_handler.py
awschain/handlers/readers/quip_reader_handler.py
awschain/handlers/readers/web_crawler_reader_handler.py
awschain/handlers/readers/youtube_reader_handler.py
awschain/handlers/writers/__init__.py
awschain/handlers/writers/amazon_datazone_asset_writer_handler.py
awschain-0.1.1.1.dist-info/LICENSE
awschain-0.1.1.1.dist-info/METADATA
awschain-0.1.1.1.dist-info/WHEEL
awschain-0.1.1.1.dist-info/top_level.txt
awschain-0.1.1.1.dist-info/RECORD
