Metadata-Version: 2.1
Name: awschain
Version: 0.1.1.1
Summary: A framework for chaining AWS services using the chain of responsibility pattern
Home-page: https://github.com/ksharlandjiev/awschain
Author: Kamen Sharlandjiev
Author-email: ksharlandjiev@gmail.com
Classifier: Development Status :: 3 - Alpha
Classifier: Intended Audience :: Developers
Classifier: License :: OSI Approved :: MIT License
Classifier: Operating System :: OS Independent
Classifier: Programming Language :: Python :: 3.8
Classifier: Programming Language :: Python :: 3.9
Requires-Python: >=3.7
License-File: LICENSE
Requires-Dist: requests
Requires-Dist: boto3
Requires-Dist: python-dotenv
